amqp/__init__.py
amqp/consumer.py
amqp/producer.py
complex_json/__init__.py
complex_json/complex_encoder.py
complex_json/complex_serializer.py
models/__init__.py
models/abstract/__init__.py
models/abstract/dto.py
models/dto/__init__.py
models/dto/customer.py
models/dto/order.py
models/dto/product.py
models/response/__init__.py
models/response/response_data.py
models/validators/__init__.py
models/validators/common_validator.py
models/validators/geoinfo_validator.py
validation/__init__.py
validation/common_validator.py
validation/geo_info_validator.py
ecommerce_common_package-1.1.8.dist-info/METADATA
ecommerce_common_package-1.1.8.dist-info/WHEEL
ecommerce_common_package-1.1.8.dist-info/top_level.txt
ecommerce_common_package-1.1.8.dist-info/RECORD
