Metadata-Version: 2.1
Name: ecommerce-common-package
Version: 1.1.8
Summary: Common package for ecommerce
Home-page: UNKNOWN
Author: Fabio Giurdanella - The BBs Way
Author-email: 
License: UNKNOWN
Platform: UNKNOWN
Requires-Dist: pika
